cog_suspect-2.1.3.data/scripts/model_summary.py
suspect/__init__.py
suspect/__version__.py
suspect/context.py
suspect/error.py
suspect/expression.py
suspect/ext.py
suspect/float_hash.py
suspect/interfaces.py
suspect/interval.py
suspect/polynomial_degree.py
suspect/propagation.py
suspect/summary.py
suspect/util.py
suspect/visitor.py
suspect/convexity/__init__.py
suspect/convexity/convexity.py
suspect/convexity/visitor.py
suspect/convexity/rules/__init__.py
suspect/convexity/rules/abs.py
suspect/convexity/rules/base.py
suspect/convexity/rules/concave.py
suspect/convexity/rules/convex.py
suspect/convexity/rules/division.py
suspect/convexity/rules/linear.py
suspect/convexity/rules/negation.py
suspect/convexity/rules/pow.py
suspect/convexity/rules/product.py
suspect/convexity/rules/quadratic.py
suspect/convexity/rules/rule.py
suspect/convexity/rules/trig.py
suspect/dag/__init__.py
suspect/dag/dag.py
suspect/dag/expressions.py
suspect/dag/iterator.py
suspect/dag/tags.py
suspect/dag/vertices_list.py
suspect/extras/__init__.py
suspect/extras/convexity/__init__.py
suspect/extras/convexity/fractional.py
suspect/extras/convexity/norm.py
suspect/extras/convexity/perspective.py
suspect/extras/convexity/quadratic.py
suspect/fbbt/__init__.py
suspect/fbbt/main.py
suspect/fbbt/initialization/__init__.py
suspect/fbbt/initialization/rules.py
suspect/fbbt/initialization/visitor.py
suspect/fbbt/propagation/__init__.py
suspect/fbbt/propagation/rules.py
suspect/fbbt/propagation/visitor.py
suspect/fbbt/tightening/__init__.py
suspect/fbbt/tightening/quadratic.py
suspect/fbbt/tightening/rules.py
suspect/fbbt/tightening/visitor.py
suspect/math/__init__.py
suspect/math/arbitrary_precision.py
suspect/math/floating_point.py
suspect/monotonicity/__init__.py
suspect/monotonicity/monotonicity.py
suspect/monotonicity/visitor.py
suspect/monotonicity/rules/__init__.py
suspect/monotonicity/rules/abs.py
suspect/monotonicity/rules/base.py
suspect/monotonicity/rules/division.py
cog_suspect-2.1.3.dist-info/LICENSE
cog_suspect-2.1.3.dist-info/METADATA
cog_suspect-2.1.3.dist-info/WHEEL
cog_suspect-2.1.3.dist-info/entry_points.txt
cog_suspect-2.1.3.dist-info/top_level.txt
cog_suspect-2.1.3.dist-info/RECORD
