Metadata-Version: 2.1
Name: cog-suspect
Version: 2.1.3
Summary: Special Structure Detection for Pyomo
Home-page: https://github.com/cog-imperial/suspect
Author: Francesco Ceccon
Author-email: francesco@ceccon.me
License: Apache 2.0
Platform: UNKNOWN
Classifier: Development Status :: 4 - Beta
Classifier: Intended Audience :: Science/Research
Classifier: Programming Language :: Python :: 3.5
Classifier: Programming Language :: Python :: 3.6
Classifier: Topic :: Scientific/Engineering :: Mathematics
License-File: LICENSE
Requires-Dist: pyomo (>=5.6)
Requires-Dist: numpy (>=1.14)
Requires-Dist: mpmath (>=1.0)
Requires-Dist: boto3 (>=1.7.4)
